flowdiagram/__init__.py
flowdiagram/__main__.py
flowdiagram-1.0.0.dist-info/LICENSE
flowdiagram-1.0.0.dist-info/METADATA
flowdiagram-1.0.0.dist-info/WHEEL
flowdiagram-1.0.0.dist-info/top_level.txt
flowdiagram-1.0.0.dist-info/RECORD
