Metadata-Version: 2.1
Name: flowdiagram
Version: 1.0.0
Summary: Python Library to generate Sequence Diagram in Command Line or Image
Home-page: https://github.com/vaseemkhn18/FlowDiagram/
Author: Vaseem Khan
Author-email: vaseemkhn18@gmail.com
License: UNKNOWN
Keywords: sequence diagram,UML diagram,flow diagram,comamnd line flow diagram
Platform: UNKNOWN
Classifier: Intended Audience :: Developers
Classifier: Intended Audience :: Telecommunications Industry
Classifier: License :: OSI Approved :: MIT License
Classifier: Natural Language :: English
Classifier: Programming Language :: Python :: 2
Classifier: Programming Language :: Python :: 3
Requires-Dist: multipledispatch (==0.6.0)
Requires-Dist: six
Requires-Dist: Pillow
